balinski_and_gomory/__init__.py
balinski_and_gomory/_cuda/__init__.py
balinski_and_gomory/_cuda/solve.cpp
balinski_and_gomory/_cuda/wrapper.py
balinski_and_gomory/_cuda/balinski-and-gomory-cuda/src/solver.cu
balinski_and_gomory/_cuda/balinski-and-gomory-cuda/src/solver.h
balinski_and_gomory/_cuda/balinski-and-gomory-cuda/src/test-random-float.cu
balinski_and_gomory/_torch/__init__.py
balinski_and_gomory/_torch/basic_solver.py
balinski_and_gomory/_torch/solver2.py
balinski_and_gomory/hylac_shortcut/__init__.py
balinski_and_gomory/hylac_shortcut/libhylac.so
balinski_and_gomory/hylac_shortcut/wrapper.py
balinski_and_gomory-0.0.8.dist-info/licenses/LICENSE
balinski_and_gomory-0.0.8.dist-info/METADATA
balinski_and_gomory-0.0.8.dist-info/WHEEL
balinski_and_gomory-0.0.8.dist-info/top_level.txt
balinski_and_gomory-0.0.8.dist-info/zip-safe
balinski_and_gomory-0.0.8.dist-info/RECORD
