Metadata-Version: 2.4
Name: balinski-and-gomory
Version: 0.0.8
Home-page: https://github.com/cestwc/primal-linear-assignment
Author: cestwc
Author-email: 80936226+cestwc@users.noreply.github.com
License: MIT
Classifier: Programming Language :: Python
Classifier: Programming Language :: Python :: 3
License-File: LICENSE
Dynamic: author
Dynamic: author-email
Dynamic: classifier
Dynamic: description
Dynamic: description-content-type
Dynamic: home-page
Dynamic: license
Dynamic: license-file
